Metadata-Version: 2.1
Name: jk-devon-mwdocgen
Version: 0.2020.6.12
Summary: This python module ...
Home-page: https://github.com/jkpubsrc/........
Author: Jürgen Knauth
Author-email: pubsrc@binary-overflow.de
License: Apache 2.0
Download-URL: https://github.com/jkpubsrc/......../tarball/0.2020.6.12
Keywords: ...
Platform: UNKNOWN
Classifier: Development Status :: 3 - Alpha
Classifier: License :: OSI Approved :: Apache Software License
